coral_pytorch/__init__.py
coral_pytorch/dataset.py
coral_pytorch/layers.py
coral_pytorch/losses.py
coral_pytorch-1.4.0.dist-info/LICENSE.txt
coral_pytorch-1.4.0.dist-info/METADATA
coral_pytorch-1.4.0.dist-info/WHEEL
coral_pytorch-1.4.0.dist-info/top_level.txt
coral_pytorch-1.4.0.dist-info/RECORD
