Metadata-Version: 2.1
Name: coral-pytorch
Version: 1.4.0
Summary: CORAL ordinal regression for PyTorch
Home-page: https://github.com/raschka-research-group/coral_pytorch
Author: Sebastian Raschka
Author-email: mail@sebastianraschka.com
License: MIT
Keywords: deep learning,pytorch,AI
Platform: any
Classifier: License :: OSI Approved :: MIT License
Classifier: Development Status :: 5 - Production/Stable
Classifier: Operating System :: Microsoft :: Windows
Classifier: Operating System :: POSIX
Classifier: Operating System :: Unix
Classifier: Operating System :: MacOS
Classifier: Programming Language :: Python :: 3.7
Classifier: Topic :: Scientific/Engineering
Classifier: Topic :: Scientific/Engineering :: Artificial Intelligence
Classifier: Topic :: Scientific/Engineering :: Information Analysis
Classifier: Topic :: Scientific/Engineering :: Image Recognition
License-File: LICENSE.txt
Requires-Dist: setuptools
Provides-Extra: docs
Requires-Dist: mkdocs ; extra == 'docs'
Provides-Extra: testing
Requires-Dist: pytest ; extra == 'testing'
